odoo/addons/sale_stock_product_recommendation/README.rst
odoo/addons/sale_stock_product_recommendation/__init__.py
odoo/addons/sale_stock_product_recommendation/__manifest__.py
odoo/addons/sale_stock_product_recommendation/i18n/es.po
odoo/addons/sale_stock_product_recommendation/i18n/it.po
odoo/addons/sale_stock_product_recommendation/i18n/sale_stock_product_recommendation.pot
odoo/addons/sale_stock_product_recommendation/readme/CONTRIBUTORS.md
odoo/addons/sale_stock_product_recommendation/readme/CREDITS.md
odoo/addons/sale_stock_product_recommendation/readme/DESCRIPTION.md
odoo/addons/sale_stock_product_recommendation/readme/ROADMAP.md
odoo/addons/sale_stock_product_recommendation/readme/USAGE.md
odoo/addons/sale_stock_product_recommendation/static/description/icon.png
odoo/addons/sale_stock_product_recommendation/static/description/index.html
odoo/addons/sale_stock_product_recommendation/wizards/__init__.py
odoo/addons/sale_stock_product_recommendation/wizards/sale_order_recommendation.py
odoo/addons/sale_stock_product_recommendation/wizards/sale_order_recommendation_view.xml
odoo_addon_sale_stock_product_recommendation-16.0.1.0.1.dist-info/METADATA
odoo_addon_sale_stock_product_recommendation-16.0.1.0.1.dist-info/WHEEL
odoo_addon_sale_stock_product_recommendation-16.0.1.0.1.dist-info/top_level.txt
odoo_addon_sale_stock_product_recommendation-16.0.1.0.1.dist-info/RECORD
